README.md
README.rst
setup.py
pyover/__init__.py
pyover/pyover.py
pyoverloader.egg-info/PKG-INFO
pyoverloader.egg-info/SOURCES.txt
pyoverloader.egg-info/dependency_links.txt
pyoverloader.egg-info/top_level.txt