Metadata-Version: 1.0
Name: pyoverloader
Version: 1.0.2
Summary: Another python overloading library
Home-page: https://github.com/Dmitry450/pyover
Author: /in/dev/
Author-email: bdmitry450@gmail.com
License: UNKNOWN
Platform: UNKNOWN
